<DOMSymbolItem xmlns:xsi="http://www.w3.org/2001/XMLSchema-instance" xmlns="http://ns.adobe.com/xfl/2008/" name="000_MainObjects/AboutView" itemID="548bf4a8-000001d6" lastModified="1418463412" lastUniqueIdentifier="1">
  <timeline>
    <DOMTimeline name="AboutView" currentFrame="141">
      <layers>
        <DOMLayer name="圖層 3" color="#FF800A" locked="true" current="true" isSelected="true" layerType="mask">
          <frames>
            <DOMFrame index="0" duration="200" keyMode="9728">
              <elements>
                <DOMShape>
                  <fills>
                    <FillStyle index="1">
                      <SolidColor color="#FF0000" alpha="0"/>
                    </FillStyle>
                  </fills>
                  <edges>
                    <Edge fillStyle1="1" edges="!3200 -4800S2|3200 4800!3200 4800|-3200 4800!-3200 4800|-3200 -4800!-3200 -4800|3200 -4800"/>
                  </edges>
                </DOMShape>
              </elements>
            </DOMFrame>
          </frames>
        </DOMLayer>
        <DOMLayer name="圖層 2" color="#9933CC" parentLayerIndex="0" locked="true" animationType="motion object">
          <frames>
            <DOMFrame index="0" duration="200" tweenType="motion object" motionTweenRotate="none" motionTweenScale="false" isMotionObject="true" visibleAnimationKeyframes="2097151" keyMode="8195">
              <motionObjectXML><AnimationCore TimeScale="24000" Version="1" duration="200000"><TimeMap strength="0" type="Quadratic"/><metadata><names><name langID="zh_TW" value=""/></names><Settings orientToPath="0" xformPtXOffsetPct="0.499908" xformPtYOffsetPct="0.5" xformPtZOffsetPixels="0"/></metadata><PropertyContainer id="headContainer"><PropertyContainer id="Basic_Motion"><Property enabled="1" id="Motion_X" ignoreTimeMap="0" readonly="0" visible="1"><Keyframe anchor="0,0" next="0,0" previous="0,0" roving="0" timevalue="0"/><Keyframe anchor="0,0" next="0,0" previous="0,0" roving="0" timevalue="199000"/></Property><Property enabled="1" id="Motion_Y" ignoreTimeMap="0" readonly="0" visible="1"><Keyframe anchor="0,0" next="0,0" previous="0,0" roving="0" timevalue="0"/><Keyframe anchor="0,-828.8" next="0,-828.8" previous="0,-828.8" roving="0" timevalue="199000"/></Property><Property enabled="1" id="Rotation_Z" ignoreTimeMap="0" readonly="0" visible="1"><Keyframe anchor="0,0" next="0,0" previous="0,0" roving="0" timevalue="0"/></Property></PropertyContainer><PropertyContainer id="Transformation"><Property enabled="1" id="Skew_X" ignoreTimeMap="0" readonly="0" visible="1"><Keyframe anchor="0,0" next="0,0" previous="0,0" roving="0" timevalue="0"/></Property><Property enabled="1" id="Skew_Y" ignoreTimeMap="0" readonly="0" visible="1"><Keyframe anchor="0,0" next="0,0" previous="0,0" roving="0" timevalue="0"/></Property><Property enabled="1" id="Scale_X" ignoreTimeMap="0" readonly="0" visible="1"><Keyframe anchor="0,100" next="0,100" previous="0,100" roving="0" timevalue="0"/></Property><Property enabled="1" id="Scale_Y" ignoreTimeMap="0" readonly="0" visible="1"><Keyframe anchor="0,100" next="0,100" previous="0,100" roving="0" timevalue="0"/></Property></PropertyContainer><PropertyContainer id="Colors"><PropertyContainer id="Alpha_ColorXform"><Property enabled="1" id="Alpha_Amount" ignoreTimeMap="0" readonly="0" visible="1"><Keyframe anchor="0,0" next="0,0" previous="0,0" roving="0" timevalue="0"/><Keyframe anchor="0,100" next="0,100" previous="0,100" roving="0" timevalue="9000"/><Keyframe anchor="0,100" next="0,100" previous="0,100" roving="0" timevalue="190000"/><Keyframe anchor="0,0" next="0,0" previous="0,0" roving="0" timevalue="199000"/></Property></PropertyContainer></PropertyContainer><PropertyContainer id="Filters"/></PropertyContainer></AnimationCore></motionObjectXML>
              <elements>
                <DOMSymbolInstance libraryItemName="About" name="" centerPoint3DX="-0.05" centerPoint3DY="432.6">
                  <matrix>
                    <Matrix ty="150.85"/>
                  </matrix>
                  <transformationPoint>
                    <Point x="-0.05" y="281.75"/>
                  </transformationPoint>
                  <color>
                    <Color alphaMultiplier="0"/>
                  </color>
                </DOMSymbolInstance>
              </elements>
            </DOMFrame>
          </frames>
        </DOMLayer>
        <DOMLayer name="BG" color="#4FFF4F" autoNamed="false">
          <frames>
            <DOMFrame index="0" duration="200" keyMode="9728">
              <elements>
                <DOMShape>
                  <fills>
                    <FillStyle index="1">
                      <SolidColor color="#FFFFFF"/>
                    </FillStyle>
                  </fills>
                  <edges>
                    <Edge fillStyle1="1" edges="!8750 953|8750 2215!8750 2215|6927 2215!6927 2215|6927 953!6927 953|8750 953"/>
                  </edges>
                </DOMShape>
                <DOMBitmapInstance name="" referenceID="" libraryItemName="001_Textures/AboutView/AboutBackground.png">
                  <matrix>
                    <Matrix tx="-160" ty="-240"/>
                  </matrix>
                </DOMBitmapInstance>
              </elements>
            </DOMFrame>
          </frames>
        </DOMLayer>
      </layers>
    </DOMTimeline>
  </timeline>
</DOMSymbolItem>